odat/__init__.py
odat/defaults.py
odat/install.py
odat/util.py
odat/mdat/__init__.py
odat/mdat/conveyor_belts_01.py
odat/mdat/iatis.py
odat/mdat/ss.py
odat/mdat/xe.py
odat/utils/__init__.py
odat/utils/chunkers.py
odat/utils/spectro.py
odat-0.0.9.dist-info/LICENSE
odat-0.0.9.dist-info/METADATA
odat-0.0.9.dist-info/WHEEL
odat-0.0.9.dist-info/top_level.txt
odat-0.0.9.dist-info/RECORD
