Metadata-Version: 2.1
Name: odat
Version: 0.0.9
Summary: Getting sound/vibration data simply
Home-page: https://github.com/otosense/odat
Author: Otosense
Author-email: thor@otosense.com
License: MIT
Keywords: data,data access,data preperation,machine learning,artificial intelligence
Platform: any
